zzq_string_sum-0.4.0.dist-info/METADATA
zzq_string_sum-0.4.0.dist-info/WHEEL
databus/__init__.py
databus/databus.cpython-39-i386-linux-gnu.so
zzq_string_sum-0.4.0.dist-info/RECORD
